cognite/extractorutils/mqtt/__init__.py
cognite/extractorutils/mqtt/extractor.py
cognite/extractorutils/mqtt/mqtt.py
cognite_extractor_utils_mqtt-0.1.0.dist-info/LICENSE
cognite_extractor_utils_mqtt-0.1.0.dist-info/WHEEL
cognite_extractor_utils_mqtt-0.1.0.dist-info/METADATA
cognite_extractor_utils_mqtt-0.1.0.dist-info/RECORD
