Metadata-Version: 2.1
Name: cognite-extractor-utils-mqtt
Version: 0.1.0
Summary: MQTT extension for the Cognite extractor-utils framework
Home-page: https://github.com/cognitedata/python-extractor-utils-mqtt
License: Apache-2.0
Author: Einar Omang
Author-email: einar.omang@cognite.com
Requires-Python: >=3.7,<3.11
Classifier: License :: OSI Approved :: Apache Software License
Classifier: Programming Language :: Python :: 3
Classifier: Programming Language :: Python :: 3.10
Classifier: Programming Language :: Python :: 3.7
Classifier: Programming Language :: Python :: 3.8
Classifier: Programming Language :: Python :: 3.9
Requires-Dist: cognite-extractor-utils (>=2.1.3,<3.0.0)
Requires-Dist: paho-mqtt (>=1.6.1,<2.0.0)
Project-URL: Repository, https://github.com/cognitedata/python-extractor-utils-mqtt
